{
    "type": "item",
    "item_id": "100284",
    "source_urls": {
        "rotool": "https:\/\/rotool.gungho.jp\/item\/100284\/"
    },
    "name": "シューズスクロールI",
    "classification": {
        "is_equipment": false,
        "is_card": false,
        "card_slot_count": null,
        "enchant_slot_count": null,
        "equipment_group": null,
        "support_equipment_type": null,
        "positions": {},
        "refineable": null,
        "refine_range": null,
        "is_two_handed_weapon": false,
        "equip_jobs": null,
        "card_attachable_equipment": [],
        "card_attachable_positions": {}
    },
    "description": "魔物の魔力から生まれた\n謎のスクロール。\n特定の靴の\n隠された力を\n引き出すことができる。\n・効果\n対象アイテムにランダム\nオプションを付与する\n・対象アイテム\n勇者のウンゴリアントブーツ\n勇者の銀狐革ブーツ\n勇者のネペンテスブーツ",
    "description_lines": [
        "魔物の魔力から生まれた",
        "謎のスクロール。",
        "特定の靴の",
        "隠された力を",
        "引き出すことができる。",
        "・効果",
        "対象アイテムにランダム",
        "オプションを付与する",
        "・対象アイテム",
        "勇者のウンゴリアントブーツ",
        "勇者の銀狐革ブーツ",
        "勇者のネペンテスブーツ"
    ],
    "properties": {
        "series": null,
        "series_normalized": [],
        "kind": null,
        "accessory": null,
        "position": null,
        "attribute": null,
        "slot": null,
        "def": null,
        "atk": null,
        "mdef": null,
        "matk": null,
        "refinement": null,
        "breakable": null,
        "weight": 1,
        "weapon_level": null,
        "required_level": null,
        "equip": [],
        "pet_food": null,
        "material": null,
        "materials": [],
        "cooldown": null,
        "raw": {
            "重量": "1"
        }
    },
    "movement_restrictions": {
        "character": [],
        "storage": []
    },
    "drop_monsters": [],
    "available_maps": [],
    "source_html_sha256": "74450fb8fd7d4beda0fbf2e5c87793fc307ad06dbffbf43a73fa9be85b704d28",
    "fetched_at": "2026-05-23T09:26:15+00:00",
    "parsed_at": "2026-05-23T09:26:15+00:00"
}
