{
    "type": "item",
    "item_id": "1354",
    "source_urls": {
        "rotool": "https:\/\/rotool.gungho.jp\/item\/1354\/"
    },
    "name": "ハンマー[2]",
    "classification": {
        "is_equipment": true,
        "is_card": false,
        "card_slot_count": 2,
        "enchant_slot_count": 2,
        "equipment_group": "normal",
        "support_equipment_type": null,
        "positions": {},
        "refineable": false,
        "refine_range": null,
        "is_two_handed_weapon": false,
        "equip_jobs": {
            "all": false,
            "include_groups": {
                "swordman": true,
                "merchant": true,
                "druid": true
            },
            "include_jobs": {},
            "exclude_groups": {},
            "exclude_jobs": {}
        },
        "card_attachable_equipment": [],
        "card_attachable_positions": {}
    },
    "description": "けっこう大きな槌。",
    "description_lines": [
        "けっこう大きな槌。"
    ],
    "properties": {
        "series": "axe",
        "series_normalized": [
            "axe"
        ],
        "kind": null,
        "accessory": null,
        "position": null,
        "attribute": null,
        "slot": 2,
        "def": null,
        "atk": 120,
        "mdef": null,
        "matk": null,
        "refinement": null,
        "breakable": null,
        "weight": 200,
        "weapon_level": 2,
        "required_level": 16,
        "equip": {
            "all": false,
            "include_groups": {
                "swordman": true,
                "merchant": true,
                "druid": true
            },
            "include_jobs": {},
            "exclude_groups": {},
            "exclude_jobs": {}
        },
        "pet_food": null,
        "material": null,
        "materials": [],
        "cooldown": null,
        "raw": {
            "系列": "斧",
            "攻撃": "120",
            "重量": "200",
            "武器レベル": "2",
            "要求レベル": "16",
            "装備": "ソードマン系 マーチャント系 ドルイド系"
        }
    },
    "movement_restrictions": {
        "character": [],
        "storage": []
    },
    "drop_monsters": [],
    "available_maps": [],
    "source_html_sha256": "8622a6c8856da95837fe3226cc2598b9ff87f37cfb2523900a869934eb8e5476",
    "fetched_at": "2026-05-23T12:05:40+00:00",
    "parsed_at": "2026-05-23T12:05:40+00:00"
}
