{
    "type": "item",
    "item_id": "20193",
    "source_urls": {
        "rotool": "https:\/\/rotool.gungho.jp\/item\/20193\/"
    },
    "name": "[衣装] 小麦[0]",
    "classification": {
        "is_equipment": true,
        "is_card": false,
        "card_slot_count": 0,
        "enchant_slot_count": 4,
        "equipment_group": "support",
        "support_equipment_type": "costume",
        "positions": {
            "lower": true
        },
        "refineable": false,
        "refine_range": null,
        "is_two_handed_weapon": false,
        "equip_jobs": {
            "all": true,
            "include_groups": {},
            "include_jobs": {},
            "exclude_groups": {},
            "exclude_jobs": {}
        },
        "card_attachable_equipment": [],
        "card_attachable_positions": {}
    },
    "description": "食用農作物である小麦を\n衣装用にした物。\n食べることはできないが\n口に咥えていると\nだんだんお腹が空いてくる。",
    "description_lines": [
        "食用農作物である小麦を",
        "衣装用にした物。",
        "食べることはできないが",
        "口に咥えていると",
        "だんだんお腹が空いてくる。"
    ],
    "properties": {
        "series": "costume",
        "series_normalized": [
            "costume"
        ],
        "kind": null,
        "accessory": null,
        "position": "lower",
        "attribute": null,
        "slot": 0,
        "def": 0,
        "atk": null,
        "mdef": null,
        "matk": null,
        "refinement": null,
        "breakable": null,
        "weight": 0,
        "weapon_level": null,
        "required_level": 1,
        "equip": {
            "all": true,
            "include_groups": {},
            "include_jobs": {},
            "exclude_groups": {},
            "exclude_jobs": {}
        },
        "pet_food": null,
        "material": null,
        "materials": [],
        "cooldown": null,
        "raw": {
            "系列": "衣装",
            "防御": "0",
            "位置": "下段",
            "重量": "0",
            "要求レベル": "1",
            "装備": "全ての職業"
        }
    },
    "movement_restrictions": {
        "character": [],
        "storage": []
    },
    "drop_monsters": [],
    "available_maps": [],
    "source_html_sha256": "ebf47c6be6b0e75565b756c909ae197f73f204b83ac55eeb9047b77b9e2b0736",
    "fetched_at": "2026-05-23T16:34:15+00:00",
    "parsed_at": "2026-05-23T16:34:15+00:00"
}
