{
    "type": "item",
    "item_id": "31545",
    "source_urls": {
        "rotool": "https:\/\/rotool.gungho.jp\/item\/31545\/"
    },
    "name": "[衣装] エレメス=ガイルのスカーフ(青)[0]",
    "classification": {
        "is_equipment": true,
        "is_card": false,
        "card_slot_count": 0,
        "enchant_slot_count": 4,
        "equipment_group": "support",
        "support_equipment_type": "costume",
        "positions": {
            "lower": true
        },
        "refineable": false,
        "refine_range": null,
        "is_two_handed_weapon": false,
        "equip_jobs": {
            "all": true,
            "include_groups": {},
            "include_jobs": {},
            "exclude_groups": {},
            "exclude_jobs": {}
        },
        "card_attachable_equipment": [],
        "card_attachable_positions": {}
    },
    "description": "ボロボロに千切れている\n青い衣装用のスカーフ。\n生体工学研究所で\n目撃されたと噂に聞く\nエレメス=ガイルの物に\nよく似ている気がするが\n色が異なっているため\n恐らく勘違いだろう。",
    "description_lines": [
        "ボロボロに千切れている",
        "青い衣装用のスカーフ。",
        "生体工学研究所で",
        "目撃されたと噂に聞く",
        "エレメス=ガイルの物に",
        "よく似ている気がするが",
        "色が異なっているため",
        "恐らく勘違いだろう。"
    ],
    "properties": {
        "series": "costume",
        "series_normalized": [
            "costume"
        ],
        "kind": null,
        "accessory": null,
        "position": "lower",
        "attribute": "-",
        "slot": 0,
        "def": 0,
        "atk": null,
        "mdef": 0,
        "matk": null,
        "refinement": false,
        "breakable": false,
        "weight": 0,
        "weapon_level": null,
        "required_level": 1,
        "equip": {
            "all": true,
            "include_groups": {},
            "include_jobs": {},
            "exclude_groups": {},
            "exclude_jobs": {}
        },
        "pet_food": null,
        "material": null,
        "materials": [],
        "cooldown": null,
        "raw": {
            "系列": "衣装",
            "位置": "下段",
            "属性": "-",
            "スロット": "0",
            "Def": "0",
            "Mdef": "0",
            "精錬": "不可",
            "破損": "しない",
            "重量": "0",
            "要求レベル": "1",
            "装備": "全ての職業"
        }
    },
    "movement_restrictions": {
        "character": [],
        "storage": []
    },
    "drop_monsters": [],
    "available_maps": [],
    "source_html_sha256": "2c474d9b7bbcad757cbf4f66bac9ac2f016c14dc7414079d7770a3e9e4ae7025",
    "fetched_at": "2026-05-23T11:46:27+00:00",
    "parsed_at": "2026-05-23T11:46:27+00:00"
}
