{
    "type": "item",
    "item_id": "31791",
    "source_urls": {
        "rotool": "https:\/\/rotool.gungho.jp\/item\/31791\/"
    },
    "name": "[衣装] ぶたさんマスク[0]",
    "classification": {
        "is_equipment": true,
        "is_card": false,
        "card_slot_count": 0,
        "enchant_slot_count": 4,
        "equipment_group": "support",
        "support_equipment_type": "costume",
        "positions": {
            "lower": true
        },
        "refineable": false,
        "refine_range": null,
        "is_two_handed_weapon": false,
        "equip_jobs": {
            "all": true,
            "include_groups": {},
            "include_jobs": {},
            "exclude_groups": {},
            "exclude_jobs": {}
        },
        "card_attachable_equipment": [],
        "card_attachable_positions": {}
    },
    "description": "ぶたさんを模した\n衣装用のマスク。\nよく見ると牙が生えており\n可愛いというだけでは\n形容しがたい魅力がある。",
    "description_lines": [
        "ぶたさんを模した",
        "衣装用のマスク。",
        "よく見ると牙が生えており",
        "可愛いというだけでは",
        "形容しがたい魅力がある。"
    ],
    "properties": {
        "series": "costume",
        "series_normalized": [
            "costume"
        ],
        "kind": null,
        "accessory": null,
        "position": "lower",
        "attribute": "-",
        "slot": 0,
        "def": 0,
        "atk": null,
        "mdef": 0,
        "matk": null,
        "refinement": false,
        "breakable": false,
        "weight": 0,
        "weapon_level": null,
        "required_level": 1,
        "equip": {
            "all": true,
            "include_groups": {},
            "include_jobs": {},
            "exclude_groups": {},
            "exclude_jobs": {}
        },
        "pet_food": null,
        "material": null,
        "materials": [],
        "cooldown": null,
        "raw": {
            "系列": "衣装",
            "位置": "下段",
            "属性": "-",
            "スロット": "0",
            "Def": "0",
            "Mdef": "0",
            "精錬": "不可",
            "破損": "しない",
            "重量": "0",
            "要求レベル": "1",
            "装備": "全ての職業"
        }
    },
    "movement_restrictions": {
        "character": [],
        "storage": []
    },
    "drop_monsters": [],
    "available_maps": [],
    "source_html_sha256": "d6c10552c314139035849077ffa9930023acec36a7e8a287af122f9239d67b3a",
    "fetched_at": "2026-05-23T12:05:40+00:00",
    "parsed_at": "2026-05-23T12:05:40+00:00"
}
