{
    "type": "item",
    "item_id": "4474",
    "source_urls": {
        "rotool": "https:\/\/rotool.gungho.jp\/item\/4474\/"
    },
    "name": "ザクダムカード",
    "classification": {
        "is_equipment": false,
        "is_card": true,
        "card_slot_count": null,
        "enchant_slot_count": null,
        "equipment_group": null,
        "support_equipment_type": null,
        "positions": {},
        "refineable": null,
        "refine_range": null,
        "is_two_handed_weapon": false,
        "equip_jobs": null,
        "card_attachable_equipment": [
            "weapon"
        ],
        "card_attachable_positions": {
            "weapon": true
        }
    },
    "description": "魔法攻撃時、\n人間形モンスター\nへのダメージ + 10%",
    "description_lines": [
        "魔法攻撃時、",
        "人間形モンスター",
        "へのダメージ + 10%"
    ],
    "properties": {
        "series": "card",
        "series_normalized": [
            "card"
        ],
        "kind": null,
        "accessory": null,
        "position": null,
        "attribute": null,
        "slot": null,
        "def": null,
        "atk": null,
        "mdef": null,
        "matk": null,
        "refinement": null,
        "breakable": null,
        "weight": 1,
        "weapon_level": null,
        "required_level": null,
        "equip": [
            "weapon"
        ],
        "pet_food": null,
        "material": null,
        "materials": [],
        "cooldown": null,
        "raw": {
            "系列": "カード",
            "装備": "武器",
            "重量": "1"
        }
    },
    "movement_restrictions": {
        "character": [],
        "storage": []
    },
    "drop_monsters": [
        {
            "name": "ザクダム",
            "url": "https:\/\/rotool.gungho.jp\/monster\/ZAKUDAM"
        }
    ],
    "available_maps": [
        {
            "name": "試練の迷宮 古代遺跡",
            "url": "https:\/\/rotool.gungho.jp\/map\/2@la_11",
            "map_code": "2@la_11"
        },
        {
            "name": "封印の迷宮 古代遺跡",
            "url": "https:\/\/rotool.gungho.jp\/map\/2@lb_12",
            "map_code": "2@lb_12"
        },
        {
            "name": "異形の迷宮 古代遺跡",
            "url": "https:\/\/rotool.gungho.jp\/map\/2@lc_11",
            "map_code": "2@lc_11"
        },
        {
            "name": "幻影の迷宮 古代遺跡",
            "url": "https:\/\/rotool.gungho.jp\/map\/2@ld211",
            "map_code": "2@ld211"
        },
        {
            "name": "幻影の迷宮 古代遺跡",
            "url": "https:\/\/rotool.gungho.jp\/map\/2@lf211",
            "map_code": "2@lf211"
        },
        {
            "name": "エンドレスタワー 3層（51～75F）",
            "url": "https:\/\/rotool.gungho.jp\/map\/3@tower",
            "map_code": "3@tower"
        },
        {
            "name": "無限の空間(ノーマル)",
            "url": "https:\/\/rotool.gungho.jp\/map\/4@infi",
            "map_code": "4@infi"
        },
        {
            "name": "ギルドダンジョン シュバルツバルド",
            "url": "https:\/\/rotool.gungho.jp\/map\/schg_dun01",
            "map_code": "schg_dun01"
        }
    ],
    "source_html_sha256": "8b811be3b367fd0a9b83cd47e24145f5dec5c882173bcf45b0ec739ca555b813",
    "fetched_at": "2026-05-23T09:26:15+00:00",
    "parsed_at": "2026-05-23T09:26:15+00:00"
}
