{
    "type": "item",
    "item_id": "480344",
    "source_urls": {
        "rotool": "https:\/\/rotool.gungho.jp\/item\/480344\/"
    },
    "name": "[衣装] 半龍王女の刃鎌[0]",
    "classification": {
        "is_equipment": true,
        "is_card": false,
        "card_slot_count": 0,
        "enchant_slot_count": 4,
        "equipment_group": "support",
        "support_equipment_type": "costume",
        "positions": {
            "garment": true
        },
        "refineable": false,
        "refine_range": null,
        "is_two_handed_weapon": false,
        "equip_jobs": {
            "all": true,
            "include_groups": {},
            "include_jobs": {},
            "exclude_groups": {},
            "exclude_jobs": {}
        },
        "card_attachable_equipment": [],
        "card_attachable_positions": {}
    },
    "description": "半龍王女メアの鎌によく似た\n衣装用の刃鎌。\n半龍王女メアが所持する\n凶星から造られた不吉な道具\nではないかといわれている。\nキャラクターに\nグラフィックが反映される",
    "description_lines": [
        "半龍王女メアの鎌によく似た",
        "衣装用の刃鎌。",
        "半龍王女メアが所持する",
        "凶星から造られた不吉な道具",
        "ではないかといわれている。",
        "キャラクターに",
        "グラフィックが反映される"
    ],
    "properties": {
        "series": "costume",
        "series_normalized": [
            "costume"
        ],
        "kind": null,
        "accessory": null,
        "position": "garment",
        "attribute": "-",
        "slot": 0,
        "def": 0,
        "atk": null,
        "mdef": 0,
        "matk": null,
        "refinement": false,
        "breakable": false,
        "weight": 0,
        "weapon_level": null,
        "required_level": 1,
        "equip": {
            "all": true,
            "include_groups": {},
            "include_jobs": {},
            "exclude_groups": {},
            "exclude_jobs": {}
        },
        "pet_food": null,
        "material": null,
        "materials": [],
        "cooldown": null,
        "raw": {
            "系列": "衣装",
            "位置": "肩にかける物",
            "属性": "-",
            "スロット": "0",
            "Def": "0",
            "Mdef": "0",
            "精錬": "不可",
            "破損": "しない",
            "重量": "0",
            "要求レベル": "1",
            "装備": "全ての職業"
        }
    },
    "movement_restrictions": {
        "character": [],
        "storage": []
    },
    "drop_monsters": [],
    "available_maps": [],
    "source_html_sha256": "fcf0f549bab7054fff57fcc5dc4e05f7d251d34ff76e8cc5dab92d9ac75bd93d",
    "fetched_at": "2026-05-23T12:22:08+00:00",
    "parsed_at": "2026-05-23T12:22:08+00:00"
}
